tamaas/__init__.py
tamaas/__main__.py
tamaas/_tamaas.cpython-38-x86_64-linux-gnu.so
tamaas/compute.py
tamaas/utils.py
tamaas/dumpers/__init__.py
tamaas/dumpers/_helper.py
tamaas/materials/__init__.py
tamaas/nonlinear_solvers/__init__.py
tamaas-2.8.1.dist-info/METADATA
tamaas-2.8.1.dist-info/WHEEL
tamaas-2.8.1.dist-info/entry_points.txt
tamaas-2.8.1.dist-info/top_level.txt
tamaas-2.8.1.dist-info/RECORD
