Metadata-Version: 2.1
Name: tamaas
Version: 2.8.1
Home-page: https://gitlab.com/tamaas
Author: Lucas Frérot, Guillaume Anciaux, Valentine Rey, Son Pham-Ba, Zichen Li, Jean-François Molinari
Author-email: lucas.frerot@sorbonne-universite.fr
Project-URL: Bug Tracker, https://gitlab.com/tamaas/tamaas/-/issues
Project-URL: Documentation, https://tamaas.readthedocs.io/en/latest/
Project-URL: Source Code, https://gitlab.com/tamaas/tamaas
Project-URL: Changes, https://gitlab.com/tamaas/tamaas/-/blob/master/CHANGELOG.md
Platform: Linux
Classifier: Intended Audience :: Science/Research
Classifier: License :: OSI Approved :: GNU Affero General Public License v3
Classifier: Programming Language :: C++
Classifier: Programming Language :: Python :: 3
Classifier: Topic :: Scientific/Engineering
Classifier: Operating System :: POSIX :: Linux
Classifier: Development Status :: 5 - Production/Stable
Provides-Extra: all
Requires-Dist: uvw ; extra == 'all'
Requires-Dist: h5py ; extra == 'all'
Requires-Dist: netCDF4 ; extra == 'all'
Requires-Dist: scipy ; extra == 'all'
Requires-Dist: mpi4py ; extra == 'all'
Provides-Extra: dumpers
Requires-Dist: uvw ; extra == 'dumpers'
Requires-Dist: h5py ; extra == 'dumpers'
Requires-Dist: netCDF4 ; extra == 'dumpers'
Provides-Extra: mpi
Requires-Dist: mpi4py ; extra == 'mpi'
Provides-Extra: solvers
Requires-Dist: scipy ; extra == 'solvers'
